swiss_common_utils/__init__.py
swiss_common_utils/datetime/__init__.py
swiss_common_utils/datetime/datetime_utils.py
swiss_common_utils/datetime/exceptions/NotATimeStringError.py
swiss_common_utils/datetime/exceptions/__init__.py
swiss_common_utils/json/__init__.py
swiss_common_utils/json/json_utils.py
swiss_common_utils/memory/__init__.py
swiss_common_utils/memory/memory_profile.py
swiss_common_utils/network/__init__.py
swiss_common_utils/network/url/__init__.py
swiss_common_utils/network/url/url_utils.py
swiss_common_utils/services/__init__.py
swiss_common_utils/services/swiss_service_base.py
swiss_common_utils/sync/__init__.py
swiss_common_utils/sync/mrow_lock/__init__.py
swiss_common_utils/sync/mrow_lock/mrow.py
swiss_common_utils/sync/mrow_lock/test_mrow.py
swiss_common_utils/yml/__init__.py
swiss_common_utils/yml/yaml_utils.py
swiss_common_utils-1.0.28.0.dist-info/LICENSE.txt
swiss_common_utils-1.0.28.0.dist-info/METADATA
swiss_common_utils-1.0.28.0.dist-info/WHEEL
swiss_common_utils-1.0.28.0.dist-info/top_level.txt
swiss_common_utils-1.0.28.0.dist-info/RECORD
