Metadata-Version: 2.1
Name: swiss-common-utils
Version: 1.0.28.0
Summary: swiss common utils
Home-page: UNKNOWN
Author: lior.yehonatan
Author-email: lior.yehonatan@inel.com
License: UNKNOWN
Platform: UNKNOWN
Requires-Python: >=3.6
Requires-Dist: bleach (==3.1.0)
Requires-Dist: certifi (==2019.3.9)
Requires-Dist: chardet (==3.0.4)
Requires-Dist: coloredlogs (==10.0)
Requires-Dist: docutils (==0.14)
Requires-Dist: humanfriendly (==4.18)
Requires-Dist: idna (==2.8)
Requires-Dist: memory-profiler (==0.55.0)
Requires-Dist: pkginfo (==1.5.0.1)
Requires-Dist: psutil (==5.6.1)
Requires-Dist: pyfiglet (==0.8.post1)
Requires-Dist: Pygments (==2.3.1)
Requires-Dist: pytimeparse (==1.1.8)
Requires-Dist: PyYAML (==5.1)
Requires-Dist: readme-renderer (==24.0)
Requires-Dist: requests (==2.21.0)
Requires-Dist: requests-toolbelt (==0.9.1)
Requires-Dist: six (==1.12.0)
Requires-Dist: tqdm (==4.31.1)
Requires-Dist: twine (==1.13.0)
Requires-Dist: urllib3 (==1.24.1)
Requires-Dist: webencodings (==0.5.1)
Requires-Dist: swiss-python (==0.0.1)
